wildberries/__init__.py
wildberries/client.py
wildberries/urls.py
wildberries-0.0.1.dist-info/LICENSE
wildberries-0.0.1.dist-info/METADATA
wildberries-0.0.1.dist-info/WHEEL
wildberries-0.0.1.dist-info/top_level.txt
wildberries-0.0.1.dist-info/RECORD
