Metadata-Version: 2.1
Name: wildberries
Version: 0.0.1
Summary: Unofficial python library for wildberries
Home-page: https://github.com/russianosint/wildberries
Author: Konstantin Belov
Author-email: russianosint@gmail.com
License: UNKNOWN
Platform: UNKNOWN
Classifier: Programming Language :: Python :: 3.8
Classifier: License :: OSI Approved :: MIT License
Classifier: Operating System :: OS Independent
Requires-Python: >=3.6
License-File: LICENSE
Requires-Dist: requests (>=2.27.1)
